py_msu_scripter_app/__init__.py
py_msu_scripter_app/__main__.py
py_msu_scripter_app/py_music_looper_runner.py
py_msu_scripter_app/sample_rate_analyzer.py
py_msu_scripter_app/version.py
py_msu_scripter_app/video_creator.py
py_msu_scripter_app-0.1.11.dist-info/METADATA
py_msu_scripter_app-0.1.11.dist-info/WHEEL
py_msu_scripter_app-0.1.11.dist-info/entry_points.txt
py_msu_scripter_app-0.1.11.dist-info/RECORD
