Metadata-Version: 2.1
Name: py-msu-scripter-app
Version: 0.1.11
Summary: 
Author: MattEqualsCoder
Author-email: mattequalscoder@gmail.com
Requires-Python: >=3.12,<4.0
Classifier: Programming Language :: Python :: 3
Classifier: Programming Language :: Python :: 3.12
Requires-Dist: moviepy (>=2.2.1,<3.0.0)
Requires-Dist: pydub (>=0.25.1,<0.26.0)
Requires-Dist: pymusiclooper (>=3.5.1,<4.0.0)
Requires-Dist: pyyaml (>=6.0.2,<7.0.0)
